{"current_time":1618871597,"success":true,"data":{"name":"صنایع الکترونیک ایران سیستم","name_en":"Iran System Electeronic Industries","logo":"/company/iran-system-electeronic-industries/081a1c60-4114-11e9-ae2f-3d431eba937c.png","cover":"/default/company/header.jpg","industry":{"name":"تولید و صنایع","industry_slug":"تولید-و-صنایع","logo":"/default/system/inudstry.jpg","icon":"fa fa-industry","description":"good industry","company_count":1598},"founded":"سال نامشخص","benefit":[],"gallery":[],"company_slug":"iran-system-electeronic-industries","city":{"name":"تهران","show_name":"تهران, تهران","city_slug":"تهران"},"size":"VS","site":"","tell":"","description":"شرکت صنایع الکترونیک ایران سیستم در سال ۱۳۸۵ تاسیس شده است و اهم فعالیت آن تولید و مونتاژ تجهیزات الکترونیکی و مخابراتی و رادیو پخش اتومبیل می باشد. دفتر مرکزی شرکت خیابان دستگردی در تهران بوده و محل کارخانه شرکت واقع در شهر قدس، بلوار کلهر می باشد.","total_review":0,"total_interview":0,"total_companyview":0,"location":[0,0],"salary_avg":0,"salary_min":0,"salary_max":0,"over_all_rate":0,"seconds_to_next_review":0,"view_count":25},"message":null,"total":null,"show_type":"TOAST","index":null}