{"current_time":1618871689,"success":true,"data":{"name":"هوش نیک","name_en":"Hooshenik","logo":"/company/hooshenik/24451b20-406d-11e9-9207-5d59991b9b29.jpg","cover":"/default/company/header.jpg","industry":{"name":"خدمات درمانی، پزشکی و سلامت","industry_slug":"خدمات-درمانی-پزشکی-و-سلامت","logo":"/default/system/inudstry.jpg","icon":"fa fa-user-md","description":"good industry","company_count":591},"founded":"سال نامشخص","benefit":[],"gallery":[],"company_slug":"hooshenik","city":{"name":"تهران","show_name":"تهران, تهران","city_slug":"تهران"},"size":"VS","site":"http://hooshenik.com","tell":"","description":"نیک ؛ اولین مرکز تخصصی تحقیقات هوش مالی کودک ایران در سال ۱۳۹۰ با همکاری جمعی از دکترین و متخصصین ایرانی در داخل و خارج از کشور تأسیس گردید. بررسی و مطالعه بیش از ۱۲۵۰۰ نفر ساعت منابع علمی از سراسر دنیا و همچنین برگزاری جلسات متعدد در موسسات علمی در امریکا و استرالیا به عنوان پیشرفته ترین مراکز شناخته شده در جهان ، پشتوانه علمی و عملیاتی مرکز تحقیقات نیک می باشد.","total_review":0,"total_interview":0,"total_companyview":0,"location":[0,0],"salary_avg":0,"salary_min":0,"salary_max":0,"over_all_rate":0,"seconds_to_next_review":0,"view_count":23},"message":null,"total":null,"show_type":"TOAST","index":null}