{"current_time":1618868095,"success":true,"data":{"name":"یوایکس پیچ","name_en":"UxpPitch","logo":"/company/uxppitch/3a33b060-40e7-11e9-b2d2-7d174071e9a1.jpg","cover":"/default/company/header.jpg","industry":{"name":"کامپیوتر، فناوری اطلاعات و اینترنت","industry_slug":"کامپیوتر-فناوری-اطلاعات-و-اینترنت","logo":"/default/system/inudstry.jpg","icon":"fa fa-code","description":"good industry","company_count":8346},"founded":"سال نامشخص","benefit":[],"gallery":[],"company_slug":"uxppitch","city":{"name":"اصفهان","show_name":"اصفهان, اصفهان","city_slug":"اصفهان"},"size":"VS","site":"http://uxpitch.com","tell":"","description":"تیم Uxpitch از سال 1395 در زمینه ارائه خدمات Ux فعالیت خود را آغاز کرد. هم اکنون مفتخریم تا با بزرگترین تیم طراحان Ux , Ui و هم چنین با بهره گیری از بهترین تیم Digital Branding و با گردآوری جمعی از نیروهای متخصص و با تجربه ی حوزه وب کامل ترین خدمات را به شما ارائه کنیم. علاوه بر این ، ارائه تخصصی ترین مشاوره های حوزه Ux برای رسیدن به بهترین نتیجه در کسب و کار شما از جمله خدمات ویژه تیم Ux Pitch می باشد.","total_review":0,"total_interview":0,"total_companyview":0,"location":[0,0],"salary_avg":0,"salary_min":0,"salary_max":0,"over_all_rate":0,"seconds_to_next_review":0,"view_count":20},"message":null,"total":null,"show_type":"TOAST","index":null}