{"current_time":1618861559,"success":true,"data":{"name":"دفتر مشاوره نرگس جوادیان","name_en":"Narges Javadian","logo":"/company/narges-javadian/45cbaae0-40e8-11e9-b89d-b1059f73c225.jpg","cover":"/default/company/header.jpg","industry":{"name":"خدمات درمانی، پزشکی و سلامت","industry_slug":"خدمات-درمانی-پزشکی-و-سلامت","logo":"/default/system/inudstry.jpg","icon":"fa fa-user-md","description":"good industry","company_count":591},"founded":"سال نامشخص","benefit":[],"gallery":[],"company_slug":"narges-javadian","city":{"name":"تهران","show_name":"تهران, تهران","city_slug":"تهران"},"size":"VS","site":"http://nargesjavadian.com","tell":"","description":"نرگس جوادیان، فارغ التحصیل رشته روانشناسی با بیش از 14 سال سابقه درمان و تدریس، دارای بورد تخصصی زوج درمانی و درمان گروهی و فردی در زمینه های افسردگی، اضطراب، مشاوره پیش از ازدواج می‌باشد.","total_review":0,"total_interview":0,"total_companyview":0,"location":[0,0],"salary_avg":0,"salary_min":0,"salary_max":0,"over_all_rate":0,"seconds_to_next_review":0,"view_count":250},"message":null,"total":null,"show_type":"TOAST","index":null}