{"current_time":1618867070,"success":true,"data":{"name":"آخرین خبر تهران","name_en":"Akharinkhabar Tehran","logo":"/company/akharinkhabar-tehran/899b0820-407d-11e9-ab14-956bff897dd5.jpg","cover":"/default/company/header.jpg","industry":{"name":"رسانه و انتشارات","industry_slug":"رسانه-و-انتشارات","logo":"/default/system/inudstry.jpg","icon":"far fa-newspaper","description":"good industry","company_count":465},"founded":"سال نامشخص","benefit":[],"gallery":[],"company_slug":"akharinkhabar-tehran","city":{"name":"تهران","show_name":"تهران, تهران","city_slug":"تهران"},"size":"VS","site":"","tell":"","description":"آخرین خبر تهران یکی از موثرترین رسانه های استانی است که با تلاش همه جانبه سعی بر خبررسانی و جریان سازی سریع و فراجناحی دارد. این بنگاه خبری در زمینه تبلیغات پربازده نیز فعالیت می کند و تاکنون با شرکت های معتبری فعالیت داشته است.","total_review":0,"total_interview":0,"total_companyview":0,"location":[0,0],"salary_avg":0,"salary_min":0,"salary_max":0,"over_all_rate":0,"seconds_to_next_review":0,"view_count":14},"message":null,"total":null,"show_type":"TOAST","index":null}