{"current_time":1618867272,"success":true,"data":{"name":"فناوری هوشمند دیبا","name_en":"Diba Smart Technology","logo":"/company/diba-smart-technology/298856f0-4058-11e9-84a1-ebe68ee40a03.jpeg","cover":"/default/company/header.jpg","industry":{"name":"کامپیوتر، فناوری اطلاعات و اینترنت","industry_slug":"کامپیوتر-فناوری-اطلاعات-و-اینترنت","logo":"/default/system/inudstry.jpg","icon":"fa fa-code","description":"good industry","company_count":8346},"founded":"سال نامشخص","benefit":[],"gallery":[],"company_slug":"diba-smart-technology","city":{"name":"تهران","show_name":"تهران, تهران","city_slug":"تهران"},"size":"VS","site":"","tell":"","description":"گروه ديبا فعالیت های خود را در زمینه های نرم افزار و شبکه های کامپیوتری از سال 1385 آغاز نمود که در ادامه جهت ارتقاء گروه به شرکت دانش بنیان، در سال 1396 با ثبت شرکت فناوری هوشمند دیبا فعالیت خود در زمینه اجرای طرح های نرم افزاری و تولید سامانه های هوشمند با جدیت و توان بیشتر ادامه داده است.","total_review":0,"total_interview":0,"total_companyview":0,"location":[0,0],"salary_avg":0,"salary_min":0,"salary_max":0,"over_all_rate":0,"seconds_to_next_review":0,"view_count":19},"message":null,"total":null,"show_type":"TOAST","index":null}