{"current_time":1618869351,"success":true,"data":{"name":"داده پردازان صبابیت","name_en":"Dade Pardazan Sababit","logo":"/company/dade-pardazan-sababit/6a6c1260-406e-11e9-97d5-3b93ab5c7818.jpg","cover":"/default/company/header.jpg","industry":{"name":"کامپیوتر، فناوری اطلاعات و اینترنت","industry_slug":"کامپیوتر-فناوری-اطلاعات-و-اینترنت","logo":"/default/system/inudstry.jpg","icon":"fa fa-code","description":"good industry","company_count":8346},"founded":"سال نامشخص","benefit":[],"gallery":[],"company_slug":"dade-pardazan-sababit","city":{"name":"تهران","show_name":"تهران, تهران","city_slug":"تهران"},"size":"VS","site":"","tell":"","description":"شرکت داده پردازان صبابیت با جمعی از نیروی جوان در صدد خدمات بهتر و تولید محصولات جدیدتر و بهتر می باشد . از جمله محصولات این شرکت مرکز تلفن ویپ صباترو ، سیستم ویدئو کنفرانس ترسیم ، تلفن نرم افزاری صبافون ، سیستم حسابداری و سی آر ام و ... می باشد","total_review":0,"total_interview":0,"total_companyview":0,"location":[0,0],"salary_avg":0,"salary_min":0,"salary_max":0,"over_all_rate":0,"seconds_to_next_review":0,"view_count":26},"message":null,"total":null,"show_type":"TOAST","index":null}