{"current_time":1618870491,"success":true,"data":{"name":"بابایو","name_en":"Babayoo Corporation","logo":"/company/babayoo-corporation/ece1e610-40f8-11e9-bb08-bd2547a8b273.png","cover":"/default/company/header.jpg","industry":{"name":"کامپیوتر، فناوری اطلاعات و اینترنت","industry_slug":"کامپیوتر-فناوری-اطلاعات-و-اینترنت","logo":"/default/system/inudstry.jpg","icon":"fa fa-code","description":"good industry","company_count":8346},"founded":"سال نامشخص","benefit":[],"gallery":[],"company_slug":"babayoo-corporation","city":{"name":"تهران","show_name":"تهران, تهران","city_slug":"تهران"},"size":"VS","site":"http://babayoo.ir","tell":"","description":"بابایو یک پلت فرم آنلاین برای فروش محصولات شرکت ها و کارخانه های تولیدی است. بابایو خدمات جامعی به تأمین کنندهای خود ارائه می کند که روش های مطالعه شده ی فروش در آن شامل کیفیت درعرضه و نمایش کالا، انبار داری آنلاین اتوماتیک و راه حل های عملی فروش بین المللی است. درحال حاضر بابایو در هفت کشور فعالیت میکند و پلت فرم آنلاین بهینه ای را برای بازاریابی دیجیتالی با موفقیت ارائه و اجرا است.","total_review":0,"total_interview":0,"total_companyview":0,"location":[0,0],"salary_avg":0,"salary_min":0,"salary_max":0,"over_all_rate":0,"seconds_to_next_review":0,"view_count":37},"message":null,"total":null,"show_type":"TOAST","index":null}