{"current_time":1618870464,"success":true,"data":{"name":"لاوین گشت","name_en":"Lavin Gasht","logo":"/company/lavin-gasht/2b687da0-4046-11e9-84fa-87459e341d78.png","cover":"/default/company/header.jpg","industry":{"name":"گردشگری و هتل ها","industry_slug":"گردشگری-و-هتل-ها","logo":"/default/system/inudstry.jpg","icon":"fas fa-hotel","description":"good industry","company_count":418},"founded":"سال نامشخص","benefit":[],"gallery":[],"company_slug":"lavin-gasht","city":{"name":"تهران","show_name":"تهران, تهران","city_slug":"تهران"},"size":"VS","site":"http://lavingasht.com","tell":"","description":"بعد از سالیان طولانی کسب تخصص و فعالیت در زمینه ها IT با صنعت گردشگری آشنا و علاقه مند شدیم و نسبت به تحقیق و فعالیت در مورد گردشگری و تلفیق این دو مهم با هم و پس از فعالیت های بسیار و با کمترین سرمایه اقدام به شروع و تاسیس دفتر نمودم و پس از گذراندن روز های سخت،البته شیرین و آموزش کارمندان و افزایش استعداد و توانایی های آنان توانستیم به یکی از آژانس های معتبر و حرفه ای با سیستم های بروز و نوین IT و اطلاعات کامل در این عرصه خدمتگزار شما باشیم.","total_review":0,"total_interview":0,"total_companyview":0,"location":[0,0],"salary_avg":0,"salary_min":0,"salary_max":0,"over_all_rate":0,"seconds_to_next_review":0,"view_count":80},"message":null,"total":null,"show_type":"TOAST","index":null}