{"current_time":1618868319,"success":true,"data":{"name":"لادسا","name_en":"Ladsa","logo":"/company/ladsa/efcc88c0-4101-11e9-b857-3ded7341ba04.jpg","cover":"/default/company/header.jpg","industry":{"name":"تولید و صنایع","industry_slug":"تولید-و-صنایع","logo":"/default/system/inudstry.jpg","icon":"fa fa-industry","description":"good industry","company_count":1598},"founded":"سال نامشخص","benefit":[],"gallery":[],"company_slug":"ladsa","city":{"name":"تهران","show_name":"تهران, تهران","city_slug":"تهران"},"size":"VS","site":"http://ladsaart.com","tell":"","description":"گروه طراحی لادسا از سال 1392 فعالیت خود را با هدف کاربردی کردن هنر نقاشی آغاز به کار کرده است. این گروه با ابداع فرآیند نوین نقاشی روی پارچه اقدام به طراحی و تولید وسایل دکور منزل و لباس با استفاده از این هنر کرده است. در حال حاضر تولیدات منحصر به فردی که تماما حاصل هنر دست نقاشان است طراحی و به هنر دوستان و هر آن کس که دوستدار زیبایی است تقدیم می کند.","total_review":0,"total_interview":0,"total_companyview":0,"location":[0,0],"salary_avg":0,"salary_min":0,"salary_max":0,"over_all_rate":0,"seconds_to_next_review":0,"view_count":29},"message":null,"total":null,"show_type":"TOAST","index":null}