{"current_time":1618862686,"success":true,"data":{"name":"تسکولو","name_en":"Taskulu","logo":"/company/taskulu/56d8bbe0-411d-11e9-8724-617a8e34a907.png","cover":"/default/company/header.jpg","industry":{"name":"کامپیوتر، فناوری اطلاعات و اینترنت","industry_slug":"کامپیوتر-فناوری-اطلاعات-و-اینترنت","logo":"/default/system/inudstry.jpg","icon":"fa fa-code","description":"good industry","company_count":8346},"founded":"سال نامشخص","benefit":[],"gallery":[],"company_slug":"taskulu","city":{"name":"تهران","show_name":"تهران, تهران","city_slug":"تهران"},"size":"VS","site":"http://taskulu.com","tell":"","description":"تسکولو نرم‌افزار آنلاین مدیریت کارها، پروژه‌ها، تیم‌ها و سازمان‌هاست. هر روز هزاران نفر برای انجام کارها و ارتباط با تیم‌شان از تسکولو استفاده می‌کنند.  ما اعتقاد داریم که همکاری تیمی، راهکار واقعی برای ایجاد تیم‌هایی با عملکرد بالا است و بنابراین می‌خواهیم به تیم‌های سراسر دنیا کمک کنیم تا با همکاری آسان، به بهترین عملکرد و بیش‌ترین بهره‌وری برسند؛ اما به‌خوبی می‌دانیم که یک ابزار قدرت‌مند و باکیفیت به‌تنهایی کافی نیست و خیال‌های خوب فقط وقتی عملی می‌شوند که فرهنگ کاری هم متحول شود.","total_review":2,"total_interview":0,"total_companyview":2,"location":[0,0],"salary_avg":6,"salary_min":3,"salary_max":9,"over_all_rate":3,"seconds_to_next_review":0,"view_count":1064},"message":null,"total":null,"show_type":"TOAST","index":null}