{"current_time":1618867035,"success":true,"data":{"name":"آرنا استدیو","name_en":"ArnaStudio","logo":"/company/arnastudio/1d491070-411f-11e9-b634-fd00862d8b09.png","cover":"/default/company/header.jpg","industry":{"name":"کامپیوتر، فناوری اطلاعات و اینترنت","industry_slug":"کامپیوتر-فناوری-اطلاعات-و-اینترنت","logo":"/default/system/inudstry.jpg","icon":"fa fa-code","description":"good industry","company_count":8346},"founded":"سال نامشخص","benefit":[],"gallery":[],"company_slug":"arnastudio","city":{"name":"رشت","show_name":"رشت, گيلان","city_slug":"رشت"},"size":"VS","site":"http://arnastudio.ir","tell":"","description":"تیم هنرهای دیجیتال آرنا استدیو ، در اواخر دی ماه سال 1393 کار خود را آغاز نمود. خدماتی که از این تیم به مشتریان ارائه می شود شامل طراحی وبسایت ، طراحی اپلیکیشن موبایل ، بازاریابی آنلاین و دیجیتال مارکتینگ ، طراحی آرم و نشان تجاری (لوگو) و ... می باشد. همچنین این تیم محصولات اختصاصی از جمله پوسته ها و افزونه های سیستم های مدیریت محتوا را تولید کرده و به فروش عمومی و اختصاصی می رساند.","total_review":0,"total_interview":0,"total_companyview":0,"location":[0,0],"salary_avg":0,"salary_min":0,"salary_max":0,"over_all_rate":0,"seconds_to_next_review":0,"view_count":22},"message":null,"total":null,"show_type":"TOAST","index":null}