{"current_time":1618869743,"success":true,"data":{"name":"گروه کسب و کار وندا","name_en":"Vanda Business Group","logo":"/company/vanda-business-group/a8364d90-4071-11e9-83cd-ad43c0227896.jpg","cover":"/default/company/header.jpg","industry":{"name":"کامپیوتر، فناوری اطلاعات و اینترنت","industry_slug":"کامپیوتر-فناوری-اطلاعات-و-اینترنت","logo":"/default/system/inudstry.jpg","icon":"fa fa-code","description":"good industry","company_count":8346},"founded":"سال نامشخص","benefit":[],"gallery":[],"company_slug":"vanda-business-group","city":{"name":"تهران","show_name":"تهران, تهران","city_slug":"تهران"},"size":"VS","site":"http://www.vandabg.ir","tell":"","description":"ارایه کننده خدمات مشاوره مدیریت و فناوری اطلاعات مالی و بانکی","total_review":0,"total_interview":0,"total_companyview":0,"location":[0,0],"salary_avg":0,"salary_min":0,"salary_max":0,"over_all_rate":0,"seconds_to_next_review":0,"view_count":84},"message":null,"total":null,"show_type":"TOAST","index":null}