{"current_time":1618871461,"success":true,"data":{"name":"آی‌تی ریسرچز","name_en":"itresearches","logo":"/company/itresearches/c0ba3290-4121-11e9-a0ec-43c5fdede061.png","cover":"/default/company/header.jpg","industry":{"name":"کامپیوتر، فناوری اطلاعات و اینترنت","industry_slug":"کامپیوتر-فناوری-اطلاعات-و-اینترنت","logo":"/default/system/inudstry.jpg","icon":"fa fa-code","description":"good industry","company_count":8346},"founded":"سال نامشخص","benefit":[],"gallery":[],"company_slug":"itresearches","city":{"name":"تهران","show_name":"تهران, تهران","city_slug":"تهران"},"size":"VS","site":"http://itresearches.ir","tell":"","description":"شرکت بین المللی و مرکز تحقیقات IT researches یک کمپانی فعال در فناوری اطلاعات و تحقیقات علوم کامپیوتر مستقر در انگلستان است که با شعبه های متعدد در کشور های مختلف پهنای وسیعی از خدمات تجاری و علمی را بر پایه هوش مصنوعی به شرکتها و سازمانها در سراسر جهان ارائه می نماید. این شرکت همکاری های گسترده ای را به عنوان همکار تجاری با شرکت های مطرح فناوری اطلاعات از جمله مایکروسافت، آی بی ام، آمازون و بیش از 30 شرکت بزرگ دیگر دارد.","total_review":0,"total_interview":0,"total_companyview":0,"location":[0,0],"salary_avg":0,"salary_min":0,"salary_max":0,"over_all_rate":0,"seconds_to_next_review":0,"view_count":38},"message":null,"total":null,"show_type":"TOAST","index":null}