{"current_time":1618871920,"success":true,"data":{"name":"وب طراحان","name_en":"ٌWeb Tarahan","logo":"/company/web-tarahan/1dbab4b0-4121-11e9-9cc7-09fb9f054353.jpg","cover":"/default/company/header.jpg","industry":{"name":"کامپیوتر، فناوری اطلاعات و اینترنت","industry_slug":"کامپیوتر-فناوری-اطلاعات-و-اینترنت","logo":"/default/system/inudstry.jpg","icon":"fa fa-code","description":"good industry","company_count":8346},"founded":"سال نامشخص","benefit":[],"gallery":[],"company_slug":"web-tarahan","city":{"name":"تهران","show_name":"تهران, تهران","city_slug":"تهران"},"size":"VS","site":"http://webtarahan.ir","tell":"","description":"شرکت طراحی و بهینه سازی سایت وب طراحان یک شرکت از نیروهای جوان است که در یک محیط کاملا دوستانه و صمیمی کارها انجام میشود .  در وب طراحان دوستی‌ها و صمیمیت‌ها باعث پیشرفت کار شده و همه اعضا تیم با هم دوست و رفیق چه در ساعت کاری و چه خارج از ساعت کاری می‌باشند .","total_review":0,"total_interview":0,"total_companyview":0,"location":[0,0],"salary_avg":0,"salary_min":0,"salary_max":0,"over_all_rate":0,"seconds_to_next_review":0,"view_count":16},"message":null,"total":null,"show_type":"TOAST","index":null}