{"current_time":1618871698,"success":true,"data":{"name":"املاک جنت آباد","name_en":"Janaat Abad","logo":"/company/janaat-abad/18706560-404b-11e9-913c-f9ea69671bbc.jpg","cover":"/default/company/header.jpg","industry":{"name":"معماری و عمران","industry_slug":"معماری-و-عمران","logo":"/default/system/inudstry.jpg","icon":"fa fa-ruler","description":"good industry","company_count":754},"founded":"سال نامشخص","benefit":[],"gallery":[],"company_slug":"janaat-abad","city":{"name":"تهران","show_name":"تهران, تهران","city_slug":"تهران"},"size":"VS","site":"","tell":"","description":"املاک جنت آباد با بیش از 3 دهه تجربه و خدمات صادقانه دارای بالاترین رضایتمندی را در منطقه 5 در میان ساکنین دارد عقد قرارداد های کاملا رسمی و قانونی زیر نظر کارشناس رسمی حقوق ثبتی (دانش آموخته دانشگاه تهران) مشـارکت در ساخت ، فروش و خرید املاک و مستغلات و ... رفع خلافی ساختمان، پایان کار و انواع جواز تجاری و اداری رفع مشکلات شهرداری و ثبتی","total_review":0,"total_interview":0,"total_companyview":0,"location":[0,0],"salary_avg":0,"salary_min":0,"salary_max":0,"over_all_rate":0,"seconds_to_next_review":0,"view_count":21},"message":null,"total":null,"show_type":"TOAST","index":null}