{"current_time":1618867459,"success":true,"data":{"name":"رایان گستر البرز دماوند","name_en":"Rayan Gostar Alborz Damavand","logo":"/company/rayan-gostar-alborz-damavand/37e1b340-4056-11e9-aca9-4f91de38947a.jpg","cover":"/default/company/header.jpg","industry":{"name":"کامپیوتر، فناوری اطلاعات و اینترنت","industry_slug":"کامپیوتر-فناوری-اطلاعات-و-اینترنت","logo":"/default/system/inudstry.jpg","icon":"fa fa-code","description":"good industry","company_count":8346},"founded":"سال نامشخص","benefit":[],"gallery":[],"company_slug":"rayan-gostar-alborz-damavand","city":{"name":"تهران","show_name":"تهران, تهران","city_slug":"تهران"},"size":"VS","site":"","tell":"","description":"شرکت رایان گستر البرز در سال 1395 با کمک 2 تن از موسسان تاسیس شد و هدف خود را ارائه ی محصولات و خدمات با کیفیت به کاربران و کارفرمایان خود درنظر گرفت و توانست در این مدتی که از شروع فعالیتش می گذرد نظر بسیاری را به محصولات مدیریتی خود جلب کند حال شرکت سعی دارد با تولید محصولاتی جدیدتر و به روز تر در بازار برنامه نویسی ایران برای خود محصولات قوی تری به وجود بیاورد.","total_review":0,"total_interview":0,"total_companyview":0,"location":[0,0],"salary_avg":0,"salary_min":0,"salary_max":0,"over_all_rate":0,"seconds_to_next_review":0,"view_count":20},"message":null,"total":null,"show_type":"TOAST","index":null}