{"current_time":1618867139,"success":true,"data":{"name":"رسانه خلاق","name_en":"Creative Media","logo":"/company/creative-media/9bdb3b20-408a-11e9-ac71-074a3e8f2339.jpg","cover":"/default/company/header.jpg","industry":{"name":"تبلیغات، بازاریابی و برندسازی","industry_slug":"تبلیغات-بازاریابی-و-برندسازی","logo":"/default/system/inudstry.jpg","icon":"fa fa-buysellads","description":"good industry","company_count":968},"founded":"سال نامشخص","benefit":[],"gallery":[],"company_slug":"creative-media","city":{"name":"تهران","show_name":"تهران, تهران","city_slug":"تهران"},"size":"VS","site":"http://rk-agency.com","tell":"","description":"In the constant ever changing market ambiance of Iran along with the entrance of multinational companies with new needs and objectives and the poverty of Iran in new trends of marketing, the need for a professional advertising agency which could be a response to the needs of today world was overtly observed.  That was why the management team of Resaneh Khallagh with 40 years of accumulated advertising experience decided to establish Resaneh Khallagh in 2011 in Tehran.","total_review":0,"total_interview":0,"total_companyview":0,"location":[0,0],"salary_avg":0,"salary_min":0,"salary_max":0,"over_all_rate":0,"seconds_to_next_review":0,"view_count":18},"message":null,"total":null,"show_type":"TOAST","index":null}