{"current_time":1618863310,"success":true,"data":[{"interviewer_rate":5,"total_rate":2,"id":78,"company":{"name":"سایت ایسام","name_en":"Esam","company_slug":"esam","logo":"/company/esam/41075590-4039-11e9-894d-e51ee63d442a.png"},"job":{"job_slug":"front-end","name":"Front end"},"title":"برخورد محترمانه ، انتظارات بالا و انفرادی","description":"چیزایی که توی اگهی بود رو کمابیش بلد بودم و رزومه فرستادم.ظاهر شرکت منو شوکه کرد . فک میکردم ایسام خیلی بهتر باشه .برخورد خوبی داشتن . انتظار بالا بود . نیاز به یکنفر داشتن که تنها بیاد سمت فرانت رو انجام بده. در واقع سایت ایسام رو با تکنولوژی جدید بروز کنه. بنده ریعکت کار میکردم ولی در سطحش ...","vote_count":1,"down_vote_count":0,"vote_state":"NONE","view_count":372,"created":"2020-02-29 11:20","my_review":false,"status":"REJECT","approved":true,"has_legal_issue":false}],"message":null,"total":1,"show_type":"TOAST","index":0}