{"current_time":1618871795,"success":true,"data":{"name":"منشور فناوری فردا","name_en":"IFTPRISM","logo":"/company/iftprism/662dc380-4102-11e9-afe2-af6ca4d87b63.png","cover":"/default/company/header.jpg","industry":{"name":"کامپیوتر، فناوری اطلاعات و اینترنت","industry_slug":"کامپیوتر-فناوری-اطلاعات-و-اینترنت","logo":"/default/system/inudstry.jpg","icon":"fa fa-code","description":"good industry","company_count":8346},"founded":"سال نامشخص","benefit":[],"gallery":[],"company_slug":"iftprism","city":{"name":"مشهد","show_name":"مشهد, خراسان رضوي","city_slug":"مشهد"},"size":"VS","site":"http://iftprism.com","tell":"","description":"شرکت دانش بنیان منشور فناوری فردا در حوزه فناوری اطلاعات و ارتباطات فعال می باشد و در زمینه طراحی نرم افزارها و بازی های موبایلی اقدام به ارائه محصول و خدمت می نماید.","total_review":0,"total_interview":0,"total_companyview":0,"location":[0,0],"salary_avg":0,"salary_min":0,"salary_max":0,"over_all_rate":0,"seconds_to_next_review":0,"view_count":51},"message":null,"total":null,"show_type":"TOAST","index":null}