{"current_time":1618870210,"success":true,"data":{"name":"گالری محسن","name_en":"Mohsen Gallery","logo":"/company/mohsen-gallery/69c8e520-411a-11e9-a4d4-2b9014739053.jpg","cover":"/default/company/header.jpg","industry":{"name":"رسانه و انتشارات","industry_slug":"رسانه-و-انتشارات","logo":"/default/system/inudstry.jpg","icon":"far fa-newspaper","description":"good industry","company_count":465},"founded":"سال نامشخص","benefit":[],"gallery":[],"company_slug":"mohsen-gallery","city":{"name":"تهران","show_name":"تهران, تهران","city_slug":"تهران"},"size":"VS","site":"http://mohsen.gallery","tell":"","description":"این گالری همواره در زمینه‌ی نمایش آثار هنرمندان برجسته معاصر در مدیوم‌های مختلف هنری از نقاشی، مجسمه و عکاسی تا ویدئوآرت، هنرهای نمایشی و رسانه‌های جدید، بسیار فعال بوده است. گالری محسن آثار بسیاری از هنرمندانش را به طور گسترده‌ای در موزه‌ها، بینال‌ها وآرت‌فِرهای دنیا به نمایش در آورده و همواره از همان ابتدای تاسیس‌اش به معرفی و نمایش آثار هنرمندان نوظهور و نیزشناخته شده پرداخته است.","total_review":0,"total_interview":0,"total_companyview":0,"location":[0,0],"salary_avg":0,"salary_min":0,"salary_max":0,"over_all_rate":0,"seconds_to_next_review":0,"view_count":19},"message":null,"total":null,"show_type":"TOAST","index":null}