{"current_time":1618866399,"success":true,"data":{"name":"اپزوب","name_en":"appzweb","logo":"/company/appzweb/51e0a050-4043-11e9-87b6-19e9fc5b79ef.jpg","cover":"/default/company/header.jpg","industry":{"name":"کامپیوتر، فناوری اطلاعات و اینترنت","industry_slug":"کامپیوتر-فناوری-اطلاعات-و-اینترنت","logo":"/default/system/inudstry.jpg","icon":"fa fa-code","description":"good industry","company_count":8346},"founded":"سال نامشخص","benefit":[],"gallery":[],"company_slug":"appzweb","city":{"name":"تهران","show_name":"تهران, تهران","city_slug":"تهران"},"size":"VS","site":"http://appzweb.ir","tell":"","description":"\"اپزوب دات آی آر\" یک شرکت نوپا و پویای دانش بنیان است که بر روی ایجاد ابزارهای قدرتمند مبتنی بر وب برای مشتریان خود ، تمرکز کرده است . این ابزارها شامل توسعه وب سایت ، وب اپلیکیشن و اپ های تلفن همراه است که مجموعه قدرتمندی را برای دیجیتال مارکتینگ ایجاد می کند .","total_review":0,"total_interview":0,"total_companyview":0,"location":[0,0],"salary_avg":0,"salary_min":0,"salary_max":0,"over_all_rate":0,"seconds_to_next_review":0,"view_count":16},"message":null,"total":null,"show_type":"TOAST","index":null}