{"current_time":1618870504,"success":true,"data":{"name":"نواندیشان فناوری ماکان","name_en":"Makan IT Group","logo":"/company/makan-it-group/ec5edfe0-404d-11e9-8165-ff5076fb5a72.png","cover":"/default/company/header.jpg","industry":{"name":"کامپیوتر، فناوری اطلاعات و اینترنت","industry_slug":"کامپیوتر-فناوری-اطلاعات-و-اینترنت","logo":"/default/system/inudstry.jpg","icon":"fa fa-code","description":"good industry","company_count":8346},"founded":"سال نامشخص","benefit":[],"gallery":[],"company_slug":"makan-it-group","city":{"name":"تهران","show_name":"تهران, تهران","city_slug":"تهران"},"size":"VS","site":"","tell":"","description":"شرکت نواندیشان فناوری ماکان به عنوان یک شرکت مجرب با بیش از یک دهه تجربه در حوزه ICT و فناوری اطلاعات و ارائه راهکار های هوشمند مبتنی بر تلفن های همراه فعالیت خود را شروع کرده و امید دارد تا بتواند با تولید نرم افزار های هوشمند در بستر های وب ، موبایل و کامپیوتر های خانگی سبک زندگی هموطنان سراسر ایران را ارتقا و بهبود بخشد","total_review":0,"total_interview":0,"total_companyview":0,"location":[0,0],"salary_avg":0,"salary_min":0,"salary_max":0,"over_all_rate":0,"seconds_to_next_review":0,"view_count":22},"message":null,"total":null,"show_type":"TOAST","index":null}