{"current_time":1618868112,"success":true,"data":{"name":"الو بازار","name_en":"Alobazar","logo":"/company/alobazar/028b7be0-40de-11e9-918c-b5ba5f43aae6.png","cover":"/default/company/header.jpg","industry":{"name":"کامپیوتر، فناوری اطلاعات و اینترنت","industry_slug":"کامپیوتر-فناوری-اطلاعات-و-اینترنت","logo":"/default/system/inudstry.jpg","icon":"fa fa-code","description":"good industry","company_count":8346},"founded":"سال نامشخص","benefit":[],"gallery":[],"company_slug":"alobazar","city":{"name":"تهران","show_name":"تهران, تهران","city_slug":"تهران"},"size":"VS","site":"http://www.alobazar.com","tell":"","description":"الو بازار فروشگاه اینترنتی","total_review":0,"total_interview":0,"total_companyview":0,"location":[0,0],"salary_avg":0,"salary_min":0,"salary_max":0,"over_all_rate":0,"seconds_to_next_review":0,"view_count":32},"message":null,"total":null,"show_type":"TOAST","index":null}