{"current_time":1618868322,"success":true,"data":{"name":"مصالح سازه","name_en":"Masaleh Sazeh","logo":"/company/masaleh-sazeh/9be84d50-407c-11e9-aecf-477bd8b922c3.jpeg","cover":"/default/company/header.jpg","industry":{"name":"معماری و عمران","industry_slug":"معماری-و-عمران","logo":"/default/system/inudstry.jpg","icon":"fa fa-ruler","description":"good industry","company_count":754},"founded":"سال نامشخص","benefit":[],"gallery":[],"company_slug":"masaleh-sazeh","city":{"name":"تهران","show_name":"تهران, تهران","city_slug":"تهران"},"size":"VS","site":"","tell":"","description":"فروش مصالح و ابزارالات ساختمانی","total_review":0,"total_interview":0,"total_companyview":0,"location":[0,0],"salary_avg":0,"salary_min":0,"salary_max":0,"over_all_rate":0,"seconds_to_next_review":0,"view_count":24},"message":null,"total":null,"show_type":"TOAST","index":null}