{"current_time":1618872781,"success":true,"data":{"name":"آریا بستر تجارت امن","name_en":"Arya Bastar Tejarat Amn","logo":"/company/arya-bastar-tejarat-amn/dcd28870-4084-11e9-810c-413090813e44.jpg","cover":"/default/company/header.jpg","industry":{"name":"کامپیوتر، فناوری اطلاعات و اینترنت","industry_slug":"کامپیوتر-فناوری-اطلاعات-و-اینترنت","logo":"/default/system/inudstry.jpg","icon":"fa fa-code","description":"good industry","company_count":8346},"founded":"سال نامشخص","benefit":[],"gallery":[],"company_slug":"arya-bastar-tejarat-amn","city":{"name":"تهران","show_name":"تهران, تهران","city_slug":"تهران"},"size":"VS","site":"http://ecokit.ir","tell":"","description":"با توجه به مشکلات موجود در روش های خرید و فروش سنتی و مشکلات صنایع داخلی در حوزه فروش کالا و ارائه خدمات و عدم وجود یک راهکار جامع برای پیاده سازی کسب و کار و تجارت الکترونیک بر آن شدیم که بسته ای کامل از کلیه روش ها، فرایندها و ابزارهای کاربردی و مدیریتی در حوزه کسب و کار الکترونیک طراحی و پیاده سازی نماییم و آن را در اختیار شرکت ها و صاحبان صنایع داخلی قرار دهیم و به این وسیله گام بلندی در زمینه حمایت از تولیدکنندگان داخلی و تحقق شعار اقتصاد مقاومتی برداریم.","total_review":0,"total_interview":0,"total_companyview":0,"location":[0,0],"salary_avg":0,"salary_min":0,"salary_max":0,"over_all_rate":0,"seconds_to_next_review":0,"view_count":28},"message":null,"total":null,"show_type":"TOAST","index":null}