{"current_time":1618869399,"success":true,"data":{"name":"پاساژ ایرانیان","name_en":"Pasazh Iranian","logo":"/company/pasazh-iranian/128e6d20-4067-11e9-b5b9-83f45fef6ebe.png","cover":"/default/company/header.jpg","industry":{"name":"کامپیوتر، فناوری اطلاعات و اینترنت","industry_slug":"کامپیوتر-فناوری-اطلاعات-و-اینترنت","logo":"/default/system/inudstry.jpg","icon":"fa fa-code","description":"good industry","company_count":8346},"founded":"سال نامشخص","benefit":[],"gallery":[],"company_slug":"pasazh-iranian","city":{"name":"تهران","show_name":"تهران, تهران","city_slug":"تهران"},"size":"VS","site":"","tell":"","description":"پاساژ ایرانیان در سال ۱۳۸۶ به صورت یک برنامه شبکه گسترده اینترنتی برای ارائه خدمات تبلیغات اینترنتی طراحی گردید. در سال ۱۳۹۶ و براساس نیاز جامعه و بازارکار ایران، تغییرات گسترده ای برای ارائه کلیه خدمات پایگاه های وب، طراحی، برنامه ریزی و اجرای تبلیغات و دیجیتال مارکتنیگ صورت پذیرفت. برخی از خدمات پاساژ ایرانیان: 1-معرفی کلیه مشاغل و ارائه خدمات متنوع در بستر پاساژ 2-مشاوره، طراحی و اجرای تبلیغات اینترنتی در پاساژ 3-مشاوره، طراحی و اجرای دفاتر کار اختصاصی 4-مشاوره، طراحی و اجرای فروشگاه اختصاصی","total_review":0,"total_interview":0,"total_companyview":0,"location":[0,0],"salary_avg":0,"salary_min":0,"salary_max":0,"over_all_rate":0,"seconds_to_next_review":0,"view_count":27},"message":null,"total":null,"show_type":"TOAST","index":null}