{"current_time":1618873239,"success":true,"data":[{"interviewer_rate":2,"total_rate":1,"id":101,"company":{"name":"ایران دوستان","name_en":"Iran Doostan Tours","company_slug":"iran-doostan-tours","logo":"/company/iran-doostan-tours/4a9f07c0-40df-11e9-b7ae-7930623d0d2d.png"},"job":{"job_slug":"تولید-محتوا","name":"تولید محتوا"},"title":"تولیدکننده محتوای ویدیویی","description":"یه بار روز اول بود با یه خانومی که تمامی دکور و ظاهر شرکت رو ادب و طرز برخوردش خلاصه شده مساحبه میکنی. تقریبا در مورد هرچیزی، علایق و سلایق و همه چیز و کمتر کاری که ازت انتظار دارند. ولی خب روز دوم همه چیز عوض میشه و تو کسایی رو میبینی که فک میکردی آخرین بار سال ها پیش، تو مرداد ماه اواسط دهه ...","vote_count":0,"down_vote_count":0,"vote_state":"NONE","view_count":328,"created":"2020-04-30 08:08","my_review":false,"status":"WORKING","approved":true,"has_legal_issue":false}],"message":null,"total":1,"show_type":"TOAST","index":0}