{"current_time":1618866626,"success":true,"data":{"name":"کوالا","name_en":"Qualla","logo":"/company/qualla/296b3fe0-4033-11e9-92e4-8113a2600ea3.jpg","cover":"/default/company/header.jpg","industry":{"name":"کامپیوتر، فناوری اطلاعات و اینترنت","industry_slug":"کامپیوتر-فناوری-اطلاعات-و-اینترنت","logo":"/default/system/inudstry.jpg","icon":"fa fa-code","description":"good industry","company_count":8346},"founded":"سال نامشخص","benefit":[],"gallery":[],"company_slug":"qualla","city":{"name":"تهران","show_name":"تهران, تهران","city_slug":"تهران"},"size":"VS","site":"http://qualla.ir","tell":"","description":"کوالا در پی ارزیابی کیفیت محصولات مصرفی خانوار است. این برنامه در پی پاسخ به نیاز کشور در ارزیابی کیفیت کالاهای عرضه شده در بازار داخلی، طراحی و آماده سازی شده است.","total_review":0,"total_interview":0,"total_companyview":0,"location":[0,0],"salary_avg":0,"salary_min":0,"salary_max":0,"over_all_rate":0,"seconds_to_next_review":0,"view_count":20},"message":null,"total":null,"show_type":"TOAST","index":null}