{"current_time":1618867007,"success":true,"data":{"name":"شرکت پرند پارسیان ایرانیان","name_en":"parand parsian iranian","logo":"/company/parand-parsian-iranian/51cd3970-4044-11e9-81e2-01dc02e7b379.png","cover":"/default/company/header.jpg","industry":{"name":"کامپیوتر، فناوری اطلاعات و اینترنت","industry_slug":"کامپیوتر-فناوری-اطلاعات-و-اینترنت","logo":"/default/system/inudstry.jpg","icon":"fa fa-code","description":"good industry","company_count":8346},"founded":"سال نامشخص","benefit":[],"gallery":[],"company_slug":"parand-parsian-iranian","city":{"name":"تهران","show_name":"تهران, تهران","city_slug":"تهران"},"size":"VS","site":"","tell":"","description":"این شرکت راه ­حل­ها و خدمات حرفه­ای مرتبط با فن­ آوری اطلاعات را ارائه می­نماید. فعالیت­های پارس تصمیم شامل ارائه خدمات مشاوره مدیریت، ارائه راه­ حل­های جامع کلید در دست، یکپارچه ­سازی سیستم­ها و خدمات پشتیبانی ٧×٢۴می­باشد. تصمیم به عنوان اولین ارائه دهنده راه حلهای BPMS و ECM، پیشتاز ارائه راه­ حل جامع مدیریت فرآیندهای کسب و کار، مدیریت جامع اسناد و محتوی، آنالیز و بهینه ­سازی فرآیندها در ایران می­باشد.","total_review":0,"total_interview":0,"total_companyview":0,"location":[0,0],"salary_avg":0,"salary_min":0,"salary_max":0,"over_all_rate":0,"seconds_to_next_review":0,"view_count":27},"message":null,"total":null,"show_type":"TOAST","index":null}