{"current_time":1618871815,"success":true,"data":{"name":"گسترش تجارت","name_en":"Gostaresh","logo":"/company/gostaresh/f2235b00-403e-11e9-b8f9-a38570583850.jpg","cover":"/default/company/header.jpg","industry":{"name":"کامپیوتر، فناوری اطلاعات و اینترنت","industry_slug":"کامپیوتر-فناوری-اطلاعات-و-اینترنت","logo":"/default/system/inudstry.jpg","icon":"fa fa-code","description":"good industry","company_count":8346},"founded":"سال نامشخص","benefit":[],"gallery":[],"company_slug":"gostaresh","city":{"name":"مشهد","show_name":"مشهد, خراسان رضوي","city_slug":"مشهد"},"size":"VS","site":"","tell":"","description":"شرکت گسترش تجارت در سال 1388 آغاز به کار نمود. از بدو تاسیس تاکنون نهایت تلاش این شرکت ارائه بهترین سرویس های وب به ایرانیان عزیز بوده است. این شرکت تمام شهرت و اعتبار خود را توسط کاربران خود به دست آورده است و در طی این سالها همواره \"رضایت مشتری\" یکی از اصول ما بوده است. شرکت بر این عقیده است که کیفیت در عصر حاضر مهمترین عامل موفقیت است و تنها راه آن رضایت مشتریان و ارائه امکانات بر اساس آخرین فن آوریهای ممکن است.","total_review":0,"total_interview":0,"total_companyview":0,"location":[0,0],"salary_avg":0,"salary_min":0,"salary_max":0,"over_all_rate":0,"seconds_to_next_review":0,"view_count":20},"message":null,"total":null,"show_type":"TOAST","index":null}