{"current_time":1618873229,"success":true,"data":{"name":"حمیم","name_en":"Hamim","logo":"/company/hamim/ef67f220-403b-11e9-ba48-850af5e17f7d.png","cover":"/default/company/header.jpg","industry":{"name":"کامپیوتر، فناوری اطلاعات و اینترنت","industry_slug":"کامپیوتر-فناوری-اطلاعات-و-اینترنت","logo":"/default/system/inudstry.jpg","icon":"fa fa-code","description":"good industry","company_count":8346},"founded":"سال نامشخص","benefit":[],"gallery":[],"company_slug":"hamim","city":{"name":"تهران","show_name":"تهران, تهران","city_slug":"تهران"},"size":"VS","site":"http://www.hamimco.ir","tell":"","description":"حمیم یک استارتاپ در زمینه مقابله با مخاطرات امنیتی سازمانی است که در سال ۹۵ توسط تیمی جوان از متخصصین امنیت و نرم‌افزار شکل گرفت و کار خود را با هدف ارائه راه‌کارهای جامع امنیتی به سازمان‌های بزرگ آغاز کرد.","total_review":2,"total_interview":1,"total_companyview":1,"location":[0,0],"salary_avg":0,"salary_min":0,"salary_max":0,"over_all_rate":0,"seconds_to_next_review":0,"view_count":803},"message":null,"total":null,"show_type":"TOAST","index":null}