{"current_time":1618861617,"success":true,"data":{"name":"گروه توسعه سرمایه گذاری انتخاب اسنوا","name_en":"Entekhab Investment Development Group Snowa","logo":"/company/entekhab-investment-development-group/2a26cf80-410e-11e9-8bfa-5341c8889392.jpg","cover":"/default/company/header.jpg","industry":{"name":"تولید و صنایع","industry_slug":"تولید-و-صنایع","logo":"/default/system/inudstry.jpg","icon":"fa fa-industry","description":"good industry","company_count":1598},"founded":"2005","benefit":[],"gallery":[],"company_slug":"entekhab-investment-development-group","city":{"name":"اصفهان","show_name":"اصفهان, اصفهان","city_slug":"اصفهان"},"size":"UL","site":"http://entekhabgroup.ir","tell":"","description":"گروه توسعه سرمایه گذاری انتخاب (Entekhab) متشکل از هلدینگ‌های لوازم خانگی، نفت و گاز و پتروشیمی، صنایع فولاد ، ساختمان و گردشگری و بازرگانی است که در بخش اجتماعی خود مجموعه هایی نظیر مجتمع پژوهشگاه و دانشگاه های انتخاب، بنیاد خیریه آلا و مرکز کنترل سرطان انتخاب (مکسا) را دارد. این گروه به عنوان یکی از شاخص ترین بازیگران اقتصادی، اجتماعی بخش خصوصی در ایران است. شرکت اسنوا (SNOWA) زیر مجموعه این گروه به عنوان پرچم دار تولید ملی ایران شناخته می شود.","total_review":1,"total_interview":0,"total_companyview":1,"location":[0,0],"salary_avg":2.3,"salary_min":2.3,"salary_max":2.3,"over_all_rate":2.8,"seconds_to_next_review":0,"view_count":2698},"message":null,"total":null,"show_type":"TOAST","index":null}