{"current_time":1618866197,"success":true,"data":{"name":"بهین سامانه فردا","name_en":"BSF","logo":"/company/bsf/6303fbf0-4100-11e9-9d47-c9d4a30f8b63.png","cover":"/default/company/header.jpg","industry":{"name":"کامپیوتر، فناوری اطلاعات و اینترنت","industry_slug":"کامپیوتر-فناوری-اطلاعات-و-اینترنت","logo":"/default/system/inudstry.jpg","icon":"fa fa-code","description":"good industry","company_count":8346},"founded":"سال نامشخص","benefit":[],"gallery":[],"company_slug":"bsf","city":{"name":"تهران","show_name":"تهران, تهران","city_slug":"تهران"},"size":"VS","site":"http://bsfcom.com/","tell":"","description":"شرکت مهندسی بهین سامانه فردا از سال 1376 تا کنون بطور متمرکز بر روی طراحی و تولید سیستمهای ضبط مکالمات تلفنی و بی‌سیم فعالیت نموده است. توسعه سیستمهای مرتبط با ضبط مکالمات مانند سیستم گویا یا مرکز تماس از سال 1383 آغاز شده و همچنان ادامه دارد. با توجه به موفقیت‌های چشم‌گیر و تکرارپذیر در طراحی محصولات حساس، این شرکت از سال 1390 اقدام به ارائه مستقل خدمات طراحی و تست سیستمهای دیجیتال به مراکز تحقیقاتی نموده است.","total_review":0,"total_interview":0,"total_companyview":0,"location":[0,0],"salary_avg":0,"salary_min":0,"salary_max":0,"over_all_rate":0,"seconds_to_next_review":0,"view_count":22},"message":null,"total":null,"show_type":"TOAST","index":null}