{"current_time":1618866176,"success":true,"data":[{"interviewer_rate":1,"total_rate":1,"id":206,"company":{"name":"تیارا استدیو","name_en":"Tiara Studio","company_slug":"tiara-studio","logo":"/company/tiara-studio/d230b020-403c-11e9-a2a4-0512e0fc2839.png"},"job":{"job_slug":"برنامه-نویس-وب","name":"برنامه نویس وب"},"title":"در باغ سبز","description":"این شرکت دوست داره بگه خیلی حرفه ایه و به همه احترام میزاره بعد زمان گذاشتن روی چالش فنی دوستان زحمت خبر دادن هم ندادن به خودشون خلاصه که زیاد گول ظاهر دوستان رو نخورید و رفتار محترمانه. سر حقوق 5 تومنی هم چونه میزدند.من حتی یکی دو بار هم پیام دادم به اون خانمی که باهمه صحبت میکنه که نتیجه مصاحبه ...","vote_count":1,"down_vote_count":0,"vote_state":"NONE","view_count":185,"created":"2020-08-02 17:10","my_review":false,"status":"NORESPONSE","approved":true,"has_legal_issue":false},{"interviewer_rate":5,"total_rate":5,"id":80,"company":{"name":"تیارا استدیو","name_en":"Tiara Studio","company_slug":"tiara-studio","logo":"/company/tiara-studio/d230b020-403c-11e9-a2a4-0512e0fc2839.png"},"job":{"job_slug":"front-end","name":"Front end"},"title":"اهمیت دادن به سلامت و همینطور رفتار مناسب","description":"بعد از تماس با بنده که تماس گیرنده هم کاملا رفتار مناسبی داشت بهم اعلام شد که قرار مصاحبه به صورت ویدیو کال از طریق گوگل دو انجام میشه که خیلی خوشحال شدم که بالاخره یه شرکت از این امکان رایگان که در اختیار ماست استفاده کرد.دقیقا راس ساعتی که قرار ویدیوکال بود با بنده تماس گرفتند مدیرعامل شرکت و ...","vote_count":1,"down_vote_count":0,"vote_state":"NONE","view_count":341,"created":"2020-03-03 12:06","my_review":false,"status":"NORESPONSE","approved":true,"has_legal_issue":false}],"message":null,"total":2,"show_type":"TOAST","index":0}