{"current_time":1618868170,"success":true,"data":{"name":"آریان نت","name_en":"Ariyan Net","logo":"/company/ariyan-net/f81570f0-4057-11e9-a3b7-e5a162f6dc72.png","cover":"/default/company/header.jpg","industry":{"name":"کامپیوتر، فناوری اطلاعات و اینترنت","industry_slug":"کامپیوتر-فناوری-اطلاعات-و-اینترنت","logo":"/default/system/inudstry.jpg","icon":"fa fa-code","description":"good industry","company_count":8346},"founded":"سال نامشخص","benefit":[],"gallery":[],"company_slug":"ariyan-net","city":{"name":"تهران","show_name":"تهران, تهران","city_slug":"تهران"},"size":"VS","site":"http://ariyannet.com","tell":"","description":"ما چالش هایی که صاحبان کسب کارهای بزرگ و کوچک دارند را شناسایی کرده و به آنها طرح هایی با توجه به تجارتشان پیشنهاد می کنیم. بیشترین تمرکز ما بر روی جلب رضایت، آسودگی و اطمینان خاطر شماست. گروه آریان نت با هدف ارائه خدمات شبکه، کامپیوتر و دوربین مدار بسته پا به این صنعت گذاشته و خود را موظف می داند که تمام تلاش خود را بر روی خدمات بیشتر و کیفیت بهتر قرار دهد تا صاحبان کار بتوانند از شبکه های مدرن و پیشرفته در حوزه ی فعالیت خود استفاده کنند.","total_review":0,"total_interview":0,"total_companyview":0,"location":[0,0],"salary_avg":0,"salary_min":0,"salary_max":0,"over_all_rate":0,"seconds_to_next_review":0,"view_count":23},"message":null,"total":null,"show_type":"TOAST","index":null}