{"current_time":1618869946,"success":true,"data":{"name":"کالای خواب لی لی رز","name_en":"Lililrose bedding","logo":"/company/lililrose-bedding/5aa57870-4079-11e9-ba86-23cb51429554.png","cover":"/default/company/header.jpg","industry":{"name":"تولید و صنایع","industry_slug":"تولید-و-صنایع","logo":"/default/system/inudstry.jpg","icon":"fa fa-industry","description":"good industry","company_count":1598},"founded":"سال نامشخص","benefit":[],"gallery":[],"company_slug":"lililrose-bedding","city":{"name":"تهران","show_name":"تهران, تهران","city_slug":"تهران"},"size":"VS","site":"http://www.lilirosebedding.com","tell":"","description":"تولیدی کالای خواب لی لی رز از سال 96 کار خود را در زمینه تولید انواع کالای خواب با بهترین کیفیت آغاز نموده است. ماموریت اصلی لی لی رز تولید بهترین محصول با بهترین طرح، متناسب با سلیقه مشتریان و ارائه تجربه ای منحصر بفرد از خرید کالای خواب می باشد. همچنین چشم انداز مجموعه صادرات محصولات به کشورهای همسایه است.","total_review":0,"total_interview":0,"total_companyview":0,"location":[0,0],"salary_avg":0,"salary_min":0,"salary_max":0,"over_all_rate":0,"seconds_to_next_review":0,"view_count":14},"message":null,"total":null,"show_type":"TOAST","index":null}