{"current_time":1618870077,"success":true,"data":{"name":"شرق رایا","name_en":"Shargh Raya","logo":"/company/shargh-raya/c112ea30-40ef-11e9-9827-c9a1afdec641.jpg","cover":"/default/company/header.jpg","industry":{"name":"کامپیوتر، فناوری اطلاعات و اینترنت","industry_slug":"کامپیوتر-فناوری-اطلاعات-و-اینترنت","logo":"/default/system/inudstry.jpg","icon":"fa fa-code","description":"good industry","company_count":8346},"founded":"سال نامشخص","benefit":[],"gallery":[],"company_slug":"shargh-raya","city":{"name":"مشهد","show_name":"مشهد, خراسان رضوي","city_slug":"مشهد"},"size":"VS","site":"http://sharghraya.com","tell":"","description":"شرق رایا تولید کننده و تامین کننده نرم افزارهای یکپارچه مدیریت منابع سازمانی با بیش از 25 سال سابقه در این حوزه می باشد.","total_review":0,"total_interview":0,"total_companyview":0,"location":[0,0],"salary_avg":0,"salary_min":0,"salary_max":0,"over_all_rate":0,"seconds_to_next_review":0,"view_count":39},"message":null,"total":null,"show_type":"TOAST","index":null}