{"current_time":1618866853,"success":true,"data":{"name":"زمین فیزیک پویا","name_en":"Zamin PHP","logo":"/company/zamin-php/b5133180-4104-11e9-aafd-b90589dee227.png","cover":"/default/company/header.jpg","industry":{"name":"معماری و عمران","industry_slug":"معماری-و-عمران","logo":"/default/system/inudstry.jpg","icon":"fa fa-ruler","description":"good industry","company_count":754},"founded":"سال نامشخص","benefit":[],"gallery":[],"company_slug":"zamin-php","city":{"name":"تهران","show_name":"تهران, تهران","city_slug":"تهران"},"size":"VS","site":"","tell":"","description":"مهندسین مشاور زمین فیزیک پویا در سال ۱۳۸۹ به طور رسمی فعالیت حرفه ای خود را در صنایع بالادستی نفت و معدن، پروژه های ژئوتکنیکی–ژئوفیزیکی خاص و ویژه در ایران و کشورهایی نظیر عمان و عراق آغاز کرده است. ارائه خدمات عملیاتی و اکتشافی و نیز انجام مطالعات در پروژه هاي مختلف عمرانی، صنعتی و معدنی توسط این شرکت در دست انجام می باشد. با توجه به سیاست های جدید این شرکت انجام امور بازرگانی و تجاری با کشور عمان نیز در دستور کار قرار گرفته است.","total_review":0,"total_interview":0,"total_companyview":0,"location":[0,0],"salary_avg":0,"salary_min":0,"salary_max":0,"over_all_rate":0,"seconds_to_next_review":0,"view_count":21},"message":null,"total":null,"show_type":"TOAST","index":null}