{"current_time":1618861576,"success":true,"data":{"name":"کادو کارت","name_en":"Kado Card","logo":"/company/kado-card/232ecca0-4036-11e9-b688-b3237d8c5018.png","cover":"/default/company/header.jpg","industry":{"name":"فروشگاهی","industry_slug":"خرده-فروشی-عمده-فروشی-و-فروشگاه-های-زنجیره-ای","logo":"/default/system/inudstry.jpg","icon":"fa fa-shopping-cart","description":"good industry","company_count":664},"founded":"سال نامشخص","benefit":[],"gallery":[],"company_slug":"kado-card","city":{"name":"تهران","show_name":"تهران, تهران","city_slug":"تهران"},"size":"VS","site":"http://kadocard.ir","tell":"","description":"از سال 93 ایده شکل گیری فروشگاه اینترنتی متفاوتی در ذهنمون شکل گرفت ؛و سال 94 سایتمون متولد شد ،بالا وپایین های زیادی داشتیم ،ولی از ابتدای امسال جدی و مصمم فعالیتمان را از سر گرفتیم و خیلی زود موفق شدیم نظر vc های مختلف رو جذب کنیم. خیلی ایده های جذاب داریم و در هر بخش دنبال نیروهای خوش فکر و متعهد هستیم.","total_review":3,"total_interview":1,"total_companyview":2,"location":[0,0],"salary_avg":2.7,"salary_min":2.7,"salary_max":2.7,"over_all_rate":1,"seconds_to_next_review":0,"view_count":1813},"message":null,"total":null,"show_type":"TOAST","index":null}