{"current_time":1618870449,"success":true,"data":{"name":"داتکو","name_en":"Datco","logo":"/company/datco/a0c1c550-40fd-11e9-8fda-f799cee28974.jpg","cover":"/default/company/header.jpg","industry":{"name":"کامپیوتر، فناوری اطلاعات و اینترنت","industry_slug":"کامپیوتر-فناوری-اطلاعات-و-اینترنت","logo":"/default/system/inudstry.jpg","icon":"fa fa-code","description":"good industry","company_count":8346},"founded":"سال نامشخص","benefit":[],"gallery":[],"company_slug":"datco","city":{"name":"تهران","show_name":"تهران, تهران","city_slug":"تهران"},"size":"VS","site":"https://datco.ir","tell":"","description":"داتیس آریانا تیم در سال 1383 با نگاهی تازه به صنعت طراحی و چاپ تاسیس شد طراحی و چاپ انواع کارتPVC از اولین فعالیتهای تیم داتکو است که حالا به تخصص این گروه تبدیل شده است. داتکو گام بعد خود را در بهره گیری از جدیدترین دستگاه های چاپ کارت برداشت .  برند خوشنام داتکو در کنار گسترش فعالیت خود در زمینه طراحی و چاپ کارت و نیز فروش بهترین دستگاه ها و مواد مربوط به این صنعت،  در سال 1396 بخش دیگر خود؛ برندینگ و مارکتینگ را هم راه اندازی کرد تا تجربه موفق خود در این زمینه را به مشتریان ارائه کند.","total_review":0,"total_interview":0,"total_companyview":0,"location":[0,0],"salary_avg":0,"salary_min":0,"salary_max":0,"over_all_rate":0,"seconds_to_next_review":0,"view_count":30},"message":null,"total":null,"show_type":"TOAST","index":null}