{"current_time":1618871991,"success":true,"data":{"name":"مرکز دیجیتال بیمه پاسارگاد (دیجی پی)","name_en":"Digipi","logo":"/company/digipi/aa82c900-4068-11e9-9b7a-739cc54b0629.png","cover":"/default/company/header.jpg","industry":{"name":"کامپیوتر، فناوری اطلاعات و اینترنت","industry_slug":"کامپیوتر-فناوری-اطلاعات-و-اینترنت","logo":"/default/system/inudstry.jpg","icon":"fa fa-code","description":"good industry","company_count":8346},"founded":"سال نامشخص","benefit":[],"gallery":[],"company_slug":"digipi","city":{"name":"تهران","show_name":"تهران, تهران","city_slug":"تهران"},"size":"VS","site":"","tell":"","description":"مرکز دیجیتال بیمه پاسارگاد (دیجی پی)، واحد ویژه خدمات رسانی آنلاین به مشتریان بیمه پاسارگاد است. خدمات دیجی پی شامل: فروش آنلاین بیمه از طریق اپلیکیشن بیمه پاسارگاد،خدمات غیر حضوری به مشتریان، خدمات پس از فروش آنلاین، باشگاه مشتریان بیمه پاسارگاد، خدمات حضوری به مشتریان بصورت اعزام کارشناس به محل، مشاوره آنلاین به مشتریان و ... پرسنل این مرکز از تعداد زیادی مشاور، کارشناس و مهندس فروشِ متخصص تشکیل شده است که در راستای خدمات رسانی به هموطنان عزیز مشغول به کار هستند.","total_review":0,"total_interview":0,"total_companyview":0,"location":[0,0],"salary_avg":0,"salary_min":0,"salary_max":0,"over_all_rate":0,"seconds_to_next_review":0,"view_count":136},"message":null,"total":null,"show_type":"TOAST","index":null}