{"current_time":1618871176,"success":true,"data":{"name":"راهبربازار","name_en":"Rahbar Bazaar","logo":"/company/rahbar-bazaar/3baf0d60-4038-11e9-b135-53f7cd422244.gif","cover":"/default/company/header.jpg","industry":{"name":"تبلیغات، بازاریابی و برندسازی","industry_slug":"تبلیغات-بازاریابی-و-برندسازی","logo":"/default/system/inudstry.jpg","icon":"fa fa-buysellads","description":"good industry","company_count":968},"founded":"سال نامشخص","benefit":[],"gallery":[],"company_slug":"rahbar-bazaar","city":{"name":"تهران","show_name":"تهران, تهران","city_slug":"تهران"},"size":"VS","site":"http://www.rahbarbazaar.com","tell":"","description":"شرکت راهبربازار با حضور ۱۵ ساله در بازار ایران، به ارائه‌ی خدمات کامل تحقیقات بازاریابی در ایران (Full-Service Marketing Research) می پردازد. حوزه کاری شرکت شامل خدمات تحقیقاتی، روش‌های کمّی، روش‌های کیفی و خدمات مشاوره‌ای است.","total_review":0,"total_interview":0,"total_companyview":0,"location":[0,0],"salary_avg":0,"salary_min":0,"salary_max":0,"over_all_rate":0,"seconds_to_next_review":0,"view_count":32},"message":null,"total":null,"show_type":"TOAST","index":null}