{"current_time":1618867450,"success":true,"data":{"name":"استارت آپ فالو","name_en":"Fallo","logo":"/company/fallo/e723e7d0-4047-11e9-a2c5-e92d918a4f92.png","cover":"/default/company/header.jpg","industry":{"name":"کامپیوتر، فناوری اطلاعات و اینترنت","industry_slug":"کامپیوتر-فناوری-اطلاعات-و-اینترنت","logo":"/default/system/inudstry.jpg","icon":"fa fa-code","description":"good industry","company_count":8346},"founded":"سال نامشخص","benefit":[],"gallery":[],"company_slug":"fallo","city":{"name":"تهران","show_name":"تهران, تهران","city_slug":"تهران"},"size":"VS","site":"","tell":"","description":"فالو یک مجله آنلاین است که کاربران در آن می توانند موضوعات یا وبسایت های مورد علاقه شان را دنبال نمایند. برخلاف سایت های جمع آوری کننده ی خبر ، فالو تنها یک سایت خبری نیست . فالو شامل الگوریتم هوشمند برای شناسایی و تخمین سلیقه ی کاربران با استفاده از ذخیره تگ ها در سرور می باشد و به این ترتیب می تواند محتوای مورد علاقه ی هر کاربر را به وی نمایش دهد، همچنین فالو سکویی جهت کسب درآمد تولید کنندگان محتوا نیز هست.","total_review":0,"total_interview":0,"total_companyview":0,"location":[0,0],"salary_avg":0,"salary_min":0,"salary_max":0,"over_all_rate":0,"seconds_to_next_review":0,"view_count":20},"message":null,"total":null,"show_type":"TOAST","index":null}