{"current_time":1618866488,"success":true,"data":{"name":"کارایاب فردا","name_en":"Kaara Yab Farda","logo":"/company/kaara-yab-farda/9fa1dc70-4085-11e9-8158-b30468bf9e16.png","cover":"/default/company/header.jpg","industry":{"name":"کامپیوتر، فناوری اطلاعات و اینترنت","industry_slug":"کامپیوتر-فناوری-اطلاعات-و-اینترنت","logo":"/default/system/inudstry.jpg","icon":"fa fa-code","description":"good industry","company_count":8346},"founded":"سال نامشخص","benefit":[],"gallery":[],"company_slug":"kaara-yab-farda","city":{"name":"تهران","show_name":"تهران, تهران","city_slug":"تهران"},"size":"VS","site":"","tell":"","description":"کارایاب فردا ، متمرکز بر روی نیروی انسانی است. این شرکت با استفاده از الگوریتم های پیشرفته جستجو به افرادی که قصد دارند کسب و کاری را آغاز نمایند بهترین محل های تشکیل این کسب و کارها را نمایش می دهند و آماری از میزان عرضه و تقاضا در آن منطقه مورد نظر فراهم می آورند.","total_review":0,"total_interview":0,"total_companyview":0,"location":[0,0],"salary_avg":0,"salary_min":0,"salary_max":0,"over_all_rate":0,"seconds_to_next_review":0,"view_count":19},"message":null,"total":null,"show_type":"TOAST","index":null}