{"current_time":1618868701,"success":true,"data":{"name":"گروه ارج گستر","name_en":"Arj Gostar Group","logo":"/company/arj-gostar-group/05f6d470-4064-11e9-a6d4-77137a9057f9.jpg","cover":"/default/company/header.jpg","industry":{"name":"کامپیوتر، فناوری اطلاعات و اینترنت","industry_slug":"کامپیوتر-فناوری-اطلاعات-و-اینترنت","logo":"/default/system/inudstry.jpg","icon":"fa fa-code","description":"good industry","company_count":8346},"founded":"سال نامشخص","benefit":[],"gallery":[],"company_slug":"arj-gostar-group","city":{"name":"مشهد","show_name":"مشهد, خراسان رضوي","city_slug":"مشهد"},"size":"VS","site":"https://arjgostar.com/","tell":"","description":"گروه ارج گستر از سال 1390 در حوزه آی تی با تیمی متخصص و خلاق فعالیت خود را در شهر مشهد آغاز نمود و در طی این سال ها اقدام به ارائه انواع خدمات به مشتریان خود داشته، خدماتی شامل : مشاوره ،طراحی و پیاده سازی نرم افزارهای تحت ویندوز ، وب و گوشی های هوشمند ،خدمات سخت افزاری و شبکه ، آموزشگاه فناوری اطلاعات و برگزاری دوره های تخصصی ، انجام امور تبلیغاتی به صورت محیطی و مجازی و پیاده سازی سیستم های مدیریتی . در این مدت موفق به پیاده سازی بیش از 200 پروژه نرم افزاری در حوزه های مختلف کسب و کار شده ایم","total_review":0,"total_interview":0,"total_companyview":0,"location":[0,0],"salary_avg":0,"salary_min":0,"salary_max":0,"over_all_rate":0,"seconds_to_next_review":0,"view_count":26},"message":null,"total":null,"show_type":"TOAST","index":null}