{"current_time":1618872054,"success":true,"data":{"name":"نقش ناب","name_en":"Naghsh Nab","logo":"/company/naghsh-nab/585f2bc0-4059-11e9-8925-a1f35759c8f2.jpg","cover":"/default/company/header.jpg","industry":{"name":"تبلیغات، بازاریابی و برندسازی","industry_slug":"تبلیغات-بازاریابی-و-برندسازی","logo":"/default/system/inudstry.jpg","icon":"fa fa-buysellads","description":"good industry","company_count":968},"founded":"سال نامشخص","benefit":[],"gallery":[],"company_slug":"naghsh-nab","city":{"name":"تهران","show_name":"تهران, تهران","city_slug":"تهران"},"size":"VS","site":"","tell":"","description":"شرکت تبلیغاتی\" نقش ناب \"با تکیه بر نیروی جوان، خلاق، تحصیلکرده، آموزش دیده و با تجربه در حوزه های مشاوره خلاق، تدوین برنامه استراتژی، طراحی کمپین های تبلیغاتی، تحقیقات بازار، طراحی گرافیک و خدمات چاپ، عکاسی تبلیغاتی و صنعتی،برندینگ، سمپلینگ، طراحی سایت و خدمات سئو،تولید محتوا، دیجیتال مارکتینگ و تبلیغات محیطی فعالیت دارد. برنامه ریزی برای اجرا و پخش کلیه خدمات تبلیغاتی به بهترین شکل ممکن در تمامی رسانه های تبلیغاتی موجود در سرتاسر کشور","total_review":0,"total_interview":0,"total_companyview":0,"location":[0,0],"salary_avg":0,"salary_min":0,"salary_max":0,"over_all_rate":0,"seconds_to_next_review":0,"view_count":22},"message":null,"total":null,"show_type":"TOAST","index":null}