{"current_time":1618937389,"success":true,"data":{"id":383,"company":{"name":"سانا گستر سبز","name_en":"Sana Gostar Sabz","company_slug":"sana-gostar-sabz","logo":"/company/sana-gostar-sabz/4c9b89a0-410b-11e9-9e10-8b1ae64bf213.png"},"job":{"job_slug":"کارآموز-وب","name":"کارآموز وب"},"pros":[],"cons":[{"id":5,"name":"بی نظمی کاری","icon":"fas fa-home","logo":"/default/system/cons.jpg","priority":1164},{"id":51,"name":"جلسات بی نتیجه","icon":null,"logo":null,"priority":806}],"status":"NORESPONSE","apply_method":"JOB_SITE","interviewer_rate":3,"total_rate":1,"title":"کارآموز وب","description":"<p>من وقتی اپلای کردم بعد از تماس، برای مصاحبه به شرکت دعوت شدم و یه تست هوش! ازم گرفتن و یه فردی اومد ازم سوال های کلی مثل کجا درس میخونی، ریاضیت قوی هست یا نه!، با چه زبان هایی کار کردی و الان چه کار میکنی پرسید بعد قرار شد که یه تست بفرستن و من انجام بدم که فرستادن و من تا 80 درصد که میتونستم انجامش دادم و براشون فرستادم ولی الان بعد از گذشت حدود یکسال هنوز خبر ندادن.</p><p>به نظر من برای شرکتی که به وقت مصاحبه شونده احترام نمیذاره که بعد از انجام پروژه حداقل یه فیدبک (مثبت یا منفی) بده، اصلا حتی رزومه هم نفرستید.</p>","asked_salary":0,"offered_salary":0,"vote_count":1,"down_vote_count":0,"vote_state":"NONE","view_count":129,"created":"2020-10-06 09:07","my_review":false,"interview_date":"2019-11-21","response_time_before_review":"2WEEK","response_time_after_review":"MORE","has_legal_issue":false,"reply":null,"reply_created":null,"total_review":3,"rate_avg":1.3333333333333333},"message":null,"total":null,"show_type":"TOAST","index":null}