{"current_time":1618867070,"success":true,"data":{"name":"ایده برتر کیوان","name_en":"MIB","logo":"/company/mib/e1b23650-4093-11e9-b5a8-e568382ed109.jpg","cover":"/default/company/header.jpg","industry":{"name":"خدمات درمانی، پزشکی و سلامت","industry_slug":"خدمات-درمانی-پزشکی-و-سلامت","logo":"/default/system/inudstry.jpg","icon":"fa fa-user-md","description":"good industry","company_count":591},"founded":"سال نامشخص","benefit":[],"gallery":[],"company_slug":"mib","city":{"name":"تهران","show_name":"تهران, تهران","city_slug":"تهران"},"size":"VS","site":"http://mibdental.ir","tell":"","description":"شرکت ایده برتر کیوان در سال 1378 با هدف واردات و توزيع تجهیزات و محصولات مدرن دندانپزشکي و همچنین آموزش علوم نوين مرتبط با حوزه دندانپزشکی، تحت نام تجاری \"MIB\" تأسيس گرديد و اکنون پس از گذشت بیش از 15 سال از فعاليت حرفه ای خود، به یکی از مطرح ترین و معتبرترين برندهای فعال در این حوزه بدل گشته است.","total_review":0,"total_interview":0,"total_companyview":0,"location":[0,0],"salary_avg":0,"salary_min":0,"salary_max":0,"over_all_rate":0,"seconds_to_next_review":0,"view_count":44},"message":null,"total":null,"show_type":"TOAST","index":null}